odoo/addons/stock_inventory_analytic/README.rst
odoo/addons/stock_inventory_analytic/__init__.py
odoo/addons/stock_inventory_analytic/__manifest__.py
odoo/addons/stock_inventory_analytic/i18n/es.po
odoo/addons/stock_inventory_analytic/i18n/pt.po
odoo/addons/stock_inventory_analytic/i18n/stock_inventory_analytic.pot
odoo/addons/stock_inventory_analytic/models/__init__.py
odoo/addons/stock_inventory_analytic/models/company.py
odoo/addons/stock_inventory_analytic/models/res_config_settings.py
odoo/addons/stock_inventory_analytic/models/stock_inventory_line.py
odoo/addons/stock_inventory_analytic/readme/CONTRIBUTORS.rst
odoo/addons/stock_inventory_analytic/readme/DESCRIPTION.rst
odoo/addons/stock_inventory_analytic/static/description/icon.png
odoo/addons/stock_inventory_analytic/static/description/index.html
odoo/addons/stock_inventory_analytic/tests/__init__.py
odoo/addons/stock_inventory_analytic/tests/test_stock_inventory_analytic.py
odoo/addons/stock_inventory_analytic/views/res_config_settings_views.xml
odoo/addons/stock_inventory_analytic/views/stock_inventory_line_view.xml
odoo14_addon_stock_inventory_analytic-14.0.1.0.3.dist-info/METADATA
odoo14_addon_stock_inventory_analytic-14.0.1.0.3.dist-info/WHEEL
odoo14_addon_stock_inventory_analytic-14.0.1.0.3.dist-info/top_level.txt
odoo14_addon_stock_inventory_analytic-14.0.1.0.3.dist-info/RECORD
